flask_jwt_extended/__init__.py
flask_jwt_extended/blacklist.py
flask_jwt_extended/config.py
flask_jwt_extended/exceptions.py
flask_jwt_extended/jwt_manager.py
flask_jwt_extended/utils.py
XJ_Flask_JWT_Extension-0.0.2.dist-info/LICENSE
XJ_Flask_JWT_Extension-0.0.2.dist-info/METADATA
XJ_Flask_JWT_Extension-0.0.2.dist-info/WHEEL
XJ_Flask_JWT_Extension-0.0.2.dist-info/top_level.txt
XJ_Flask_JWT_Extension-0.0.2.dist-info/RECORD
